rpc_common/__init__.py
rpc_common/imlf/__init__.py
rpc_common/imlf/imlf_pb2.py
rpc_common/imlf/imlf_pb2_grpc.py
rpc_common-0.0.12.dist-info/METADATA
rpc_common-0.0.12.dist-info/WHEEL
rpc_common-0.0.12.dist-info/dependency_links.txt
rpc_common-0.0.12.dist-info/top_level.txt
rpc_common-0.0.12.dist-info/RECORD
