Metadata-Version: 2.1
Name: rpc-common
Version: 0.0.12
Summary: rpc服务端和客户端使用的公共文件
Author: zhengshuiqing
Author-email: zhengshuiqing@goldwind.com.cn
License: Private
Requires-Dist: grpcio
Requires-Dist: grpcio-tools
Requires-Dist: protobuf
